{"cameraMode":{"drawMode":0,"name":"Shaded","section":"Shading Mode"},"sceneLighting":true,"audioPlay":false,"sceneViewState":{"showFog":true,"showMaterialUpdate":false,"showSkybox":true,"showFlares":true,"showImageEffects":true,"showParticleSystems":true},"in2DMode":false,"pivot":{"x":0.00016748905181884766,"y":2.7526822090148927,"z":-8.344650268554688e-7},"rotation":{"x":-0.04825318232178688,"y":0.03953862562775612,"z":-0.0019115122267976404,"w":-0.9980505108833313},"size":11.789201736450196,"orthographic":false}